<annotation>
	<folder>Fish photos</folder>
	<filename>DanielFish_41_result.jpg</filename>
	<path>C:\Users\danie\Downloads\Fish photos\Fish photos\DanielFish_41_result.jpg</path>
	<source>
		<database>Unknown</database>
	</source>
	<size>
		<width>450</width>
		<height>600</height>
		<depth>3</depth>
	</size>
	<segmented>0</segmented>
	<object>
		<name>Fish Tile</name>
		<pose>Unspecified</pose>
		<truncated>0</truncated>
		<difficult>0</difficult>
		<bndbox>
			<xmin>146</xmin>
			<ymin>235</ymin>
			<xmax>346</xmax>
			<ymax>421</ymax>
		</bndbox>
	</object>
</annotation>
