<annotation>
	<folder>peppermint-pics</folder>
	<filename>Steven_Peppermint_Pic_128.jpg</filename>
	<path>/home/steven/Documents/peppermint-pics/Steven_Peppermint_Pic_128.jpg</path>
	<source>
		<database>Unknown</database>
	</source>
	<size>
		<width>800</width>
		<height>600</height>
		<depth>3</depth>
	</size>
	<segmented>0</segmented>
	<object>
		<name>blue_mint</name>
		<pose>Unspecified</pose>
		<truncated>0</truncated>
		<difficult>0</difficult>
		<bndbox>
			<xmin>217</xmin>
			<ymin>150</ymin>
			<xmax>386</xmax>
			<ymax>320</ymax>
		</bndbox>
	</object>
</annotation>
